qwd/__init__.py
qwd/__main__.py
qwd/mykit/__init__.py
qwd-0.6.0b0.dist-info/LICENSE
qwd-0.6.0b0.dist-info/METADATA
qwd-0.6.0b0.dist-info/WHEEL
qwd-0.6.0b0.dist-info/entry_points.txt
qwd-0.6.0b0.dist-info/top_level.txt
qwd-0.6.0b0.dist-info/RECORD
