Metadata-Version: 2.1
Name: qwd
Version: 0.6.0b0
Summary: A shortcut to perform Git operations
Author-email: Nicholas Valentinus <nicho@scapeville.com>
License: MIT
Project-URL: Repository, https://github.com/nvfp/QWD
Requires-Python: >=3.8
License-File: LICENSE
